find_similar/__init__.py
find_similar/calc_functions.py
find_similar/calc_models.py
find_similar/core.py
find_similar/package.py
find_similar/tokenize.py
find_similar/examples/__init__.py
find_similar/examples/analyze.py
find_similar/examples/main.py
find_similar/examples/data/films-demo-ru.yml
find_similar/examples/data/films-demo-tr.yml
find_similar/examples/data/films-demo-ua.yml
find_similar/examples/data/films-demo.yml
find_similar/examples/data/films-description.yml
find_similar/examples/data/mock.yml
find_similar-2.2.1.dist-info/LICENSE
find_similar-2.2.1.dist-info/METADATA
find_similar-2.2.1.dist-info/WHEEL
find_similar-2.2.1.dist-info/top_level.txt
find_similar-2.2.1.dist-info/RECORD
