Metadata-Version: 2.1
Name: find-similar
Version: 2.2.1
Summary: User-friendly library to find similar objects
Home-page: https://github.com/findsimilar/find-similar
Author: findsimilar
Author-email: quill@craftsman.lol
License: MIT
Project-URL: Documentation, https://findsimilar.craftsman.lol
Project-URL: Source, https://github.com/findsimilar/find-similar
Project-URL: Tracker, https://github.com/findsimilar/find-similar/issues
Project-URL: Release notes, https://github.com/findsimilar/find-similar/releases
Project-URL: Changelog, https://github.com/findsimilar/find-similar/releases
Project-URL: Download, https://pypi.org/project/find-similar/
Keywords: python,search,machine-learning,natural-language-processing,find,words,texts,similar
Classifier: Development Status :: 5 - Production/Stable
Classifier: Intended Audience :: Developers
Classifier: License :: OSI Approved :: MIT License
Classifier: Programming Language :: Python :: 3
Classifier: Topic :: Scientific/Engineering
Classifier: Topic :: Scientific/Engineering :: Artificial Intelligence
Classifier: Topic :: Scientific/Engineering :: Information Analysis
Classifier: Topic :: Text Processing
Classifier: Topic :: Text Processing :: Linguistic
Requires-Python: >=3
License-File: LICENSE
Requires-Dist: setuptools
Requires-Dist: nltk ==3.8.1
Requires-Dist: pymorphy3 ==1.2.1
Requires-Dist: PyYAML ==6.0.1
